stac_japan_geo/__init__.py
stac_japan_geo/common.py
stac_japan_geo/stac_japan_geo.py
stac_japan_geo-0.0.2.dist-info/LICENSE
stac_japan_geo-0.0.2.dist-info/METADATA
stac_japan_geo-0.0.2.dist-info/WHEEL
stac_japan_geo-0.0.2.dist-info/entry_points.txt
stac_japan_geo-0.0.2.dist-info/top_level.txt
stac_japan_geo-0.0.2.dist-info/RECORD
